<?xml version="1.0" ?>
<document id="29452408">
  <sentence id="29452408.s0" text="The candidate genes located within the new loci were related to ocular development (regulation of transcription, DNA-templated, negative regulation of transcription by RNA polymerase II and MAP3K1) and glaucoma-related phenomuscle organ developments (biological_process, LMX1B and LOXL1).">
    <entity charOffset="84-126" id="29452408.s0.e0" ontology_id="GO_0006355" text="regulation of transcription, DNA-templated" type="GO"/>
    <entity charOffset="128-185" id="29452408.s0.e1" ontology_id="GO_0000122" text="negative regulation of transcription by RNA polymerase II" type="GO"/>
    <entity charOffset="202-210" id="29452408.s0.e2" ontology_id="HP_0000501" text="glaucoma" type="HP"/>
    <entity charOffset="224-248" id="29452408.s0.e3" ontology_id="GO_0007517" text="muscle organ development" type="GO"/>
    <entity charOffset="251-269" id="29452408.s0.e4" ontology_id="GO_0008150" text="biological_process" type="GO"/>
    <pair e1="29452408.s0.e0" e2="29452408.s0.e2" id="29452408.s0.p0" relation="true"/>
    <pair e1="29452408.s0.e1" e2="29452408.s0.e2" id="29452408.s0.p1" relation="true"/>
    <pair e1="29452408.s0.e2" e2="29452408.s0.e4" id="29452408.s0.p2" relation="true"/>
  </sentence>
</document>
